LICENSE
README.md
requirements.txt
setup.py
img2dataset/__init__.py
img2dataset/blurrer.py
img2dataset/distributor.py
img2dataset/downloader.py
img2dataset/export.py
img2dataset/logger.py
img2dataset/main.py
img2dataset/reader.py
img2dataset/resizer.py
img2dataset/writer.py
mllmdata.egg-info/PKG-INFO
mllmdata.egg-info/SOURCES.txt
mllmdata.egg-info/dependency_links.txt
mllmdata.egg-info/entry_points.txt
mllmdata.egg-info/requires.txt
mllmdata.egg-info/top_level.txt
tests/test_blurrer.py
tests/test_downloader.py
tests/test_fire.py
tests/test_main.py
tests/test_reader.py
tests/test_resizer.py
tests/test_writer.py