Metadata-Version: 2.4
Name: mllmdata
Version: 1.45.2
Summary: Easily turn a set of image urls to an image dataset
Home-page: https://github.com/lucasjinreal/img2dataset
Author: Romain Beaumont
Author-email: romain.rom1@gmail.com
License: MIT
Keywords: machine learning,computer vision,download,image,dataset
Classifier: Development Status :: 4 - Beta
Classifier: Intended Audience :: Developers
Classifier: Topic :: Scientific/Engineering :: Artificial Intelligence
Classifier: License :: OSI Approved :: MIT License
Classifier: Programming Language :: Python :: 3.6
License-File: LICENSE
Requires-Dist: tqdm<5,>=4.62.3
Requires-Dist: opencv-python-headless<5,>=4.5.5.62
Requires-Dist: fire<0.6.0,>=0.4.0
Requires-Dist: webdataset<0.3,>=0.2.5
Requires-Dist: pandas<3,>=1.1.5
Requires-Dist: pyarrow<16,>=6.0.1
Requires-Dist: exifread-nocycle<4,>=3.0.1
Requires-Dist: albumentations<2,>=1.1.0
Requires-Dist: dataclasses<1.0.0,>=0.6
Requires-Dist: wandb<0.17,>=0.16.0
Requires-Dist: fsspec
Dynamic: author
Dynamic: author-email
Dynamic: classifier
Dynamic: description
Dynamic: description-content-type
Dynamic: home-page
Dynamic: keywords
Dynamic: license
Dynamic: license-file
Dynamic: requires-dist
Dynamic: summary
